{"inkVersion":20,"root":[["\n","\n",{"->":"round_1"},["done",{"#f":5,"#n":"g-0"}],null],"done",{"round_1":[[{"#":"location: In App"},["^Heya! How are you? My name's Otis! It's great to meet you! ",{"#":"Name_Otis"},"\n","^I like your profile pic, you look super nice. ",{"#":"Name_Me"},"\n","^It's a real shame these phones don't have smell too. You can learn a lot about someone that way y'know? ",{"#":"Name_Otis"},"\n",["ev",{"^->":"round_1.0.g-0.9.$r1"},{"temp=":"$r"},"str",{"->":".^.s"},[{"#n":"$r1"}],"/str","/ev",{"*":".^.^.c-0","flg":18},{"s":["^:) ",{"->":"$r","var":true},null]}],{"c-0":["ev",{"^->":"round_1.0.g-0.c-0.$r2"},"/ev",{"temp=":"$r"},{"->":".^.^.9.s"},[{"#n":"$r2"}],{"#":"Name_Me"},{"#":"Emote_Happy"},"\n",{"->":".^.^.^.g-1"},{"#f":5}],"#f":5,"#n":"g-0"}],{"g-1":["^Hey, so would you like to chat for a bit? ",{"#":"Name_Otis"},"\n","^It's so good to get to speak to someone new, I get a little stir crazy sometimes! ",{"#":"Name_Otis"},"\n","^There's only so many times you can read White Fang before you start looking for someone to talk to... or a Yukon forest to run in. ",{"#":"Name_Otis"},"\n","ev","str","^Prefer Lassie","/str","/ev",{"*":".^.c-1","flg":20},"ev","str","^Not yet","/str","/ev",{"*":".^.c-2","flg":20},"ev","str","^Love it!","/str",{"VAR?":"smart"},5,">","/ev",{"*":".^.c-3","flg":21},{"c-1":["^I'm more of a Lassie: Come home fan ",{"#":"Name_Me"},"\n","^Oh, uh... yeah. I-I like that one too... ",{"#":"Name_Otis"},"\n","ev",{"VAR?":"affinity"},2,"-","/ev",{"VAR=":"affinity","re":true},"done",{"#f":5}],"c-2":["^I've been meaning to read that one! ",{"#":"Name_Me"},"\n","^You really should! It's so good it makes me want to bark! ",{"#":"Name_Otis -> round_2"},"\n",{"#f":5}],"c-3":["^I love that story, but Beauty Smith is a monster. >:| ",{"#":"Name_Me"},"\n","^But Scott is such a good person, you need a terrible villian to show him against. ",{"#":"Name_Otis"},"\n","ev",{"VAR?":"affinity"},2,"+","/ev",{"VAR=":"affinity","re":true},"done",{"#f":5}],"#f":5}]}],{"#f":1}],"round_2":[{"#":"location: Holbrook Shelter"},{"->":".^.part_1"},{"part_1":[[["^As you enter the Holbrook Shelter you see a little black and brown Dachshund playing with another dog.","\n","^When you approach he notices you and gives an ","ev",{"VAR?":"affinity"},5,">","/ev",[{"->":".^.b","c":true},{"b":["^ excited ",{"->":".^.^.^.10"},null]}],[{"->":".^.b"},{"b":["^ nervous ",{"->":".^.^.^.10"},null]}],"nop","^ wag of his tail.","\n","^Oh hey! It's so good to see you! I ","ev",{"VAR?":"affinity"},5,">","/ev",[{"->":".^.b","c":true},{"b":["^ really ",{"->":".^.^.^.20"},null]}],"nop","^ enjoyed our chat together. I was hoping I'd get to meet you in person. ",{"#":"Name_Otis"},"\n",["ev",{"^->":"round_2.part_1.0.g-0.24.$r1"},{"temp=":"$r"},"str",{"->":".^.s"},[{"#n":"$r1"}],"/str","/ev",{"*":".^.^.c-0","flg":18},{"s":["^Ask about friend ",{"->":"$r","var":true},null]}],{"c-0":["ev",{"^->":"round_2.part_1.0.g-0.c-0.$r2"},"/ev",{"temp=":"$r"},{"->":".^.^.24.s"},[{"#n":"$r2"}],{"#":"Name_Me"},"\n",{"->":".^.^.^.g-1"},{"#f":5}],"#f":5,"#n":"g-0"}],{"g-1":["^That's ","ev",{"VAR?":"betty_available"},"/ev",[{"->":".^.b","c":true},{"b":["^ Betty ",{"->":".^.^.^.6"},null]}],[{"->":".^.b"},{"b":["^ Hatty ",{"->":".^.^.^.6"},null]}],"nop","^, she and I started a book club together... Only, we're the only ones to join. ",{"#":"Name_Otis"},"\n","^Oh, but it's still great to talk about new books! ",{"#":"Name_Me"},"\n","^Say, do you have any other dogs at home? ",{"#":"Name_Otis"},"\n",["ev",{"^->":"round_2.part_1.0.g-1.16.$r1"},{"temp=":"$r"},"str",{"->":".^.s"},[{"#n":"$r1"}],"/str",{"VAR?":"has_dog"},"/ev",{"*":".^.^.c-1","flg":19},{"s":["^Yes! A house isn't a home without a dog. ",{"->":"$r","var":true},null]}],["ev",{"^->":"round_2.part_1.0.g-1.17.$r1"},{"temp=":"$r"},"str",{"->":".^.s"},[{"#n":"$r1"}],"/str","/ev",{"*":".^.^.c-2","flg":18},{"s":["^No, but I wouldn't mind more. ",{"->":"$r","var":true},null]}],["ev",{"^->":"round_2.part_1.0.g-1.18.$r1"},{"temp=":"$r"},"str",{"->":".^.s"},[{"#n":"$r1"}],"/str","/ev",{"*":".^.^.c-3","flg":18},{"s":["^No, one doggo is enough of a handful for me! ",{"->":"$r","var":true},null]}],{"c-1":["ev",{"^->":"round_2.part_1.0.g-1.c-1.$r2"},"/ev",{"temp=":"$r"},{"->":".^.^.16.s"},[{"#n":"$r2"}],{"#":"Name_Me"},"\n","ev",{"VAR?":"affinity"},1,"+","/ev",{"VAR=":"affinity","re":true},"^Oh how wonderful! I should have known. I can even smell them on you. I'd love to meet them sometime. ",{"#":"Name_Otis"},"\n",{"->":"round_2.part_2"},{"#f":5}],"c-2":["ev",{"^->":"round_2.part_1.0.g-1.c-2.$r2"},"/ev",{"temp=":"$r"},{"->":".^.^.17.s"},[{"#n":"$r2"}],{"#":"Name_Me"},"\n","^That's a bit sad, but perhaps we could find another forever friend together? ",{"#":"Name_Otis"},"\n",{"->":"round_2.part_2"},{"#f":5}],"c-3":["ev",{"^->":"round_2.part_1.0.g-1.c-3.$r2"},"/ev",{"temp=":"$r"},{"->":".^.^.18.s"},[{"#n":"$r2"}],{"#":"Name_Me"},"\n","^Oh... That's a bit sad. ",{"#":"Name_Otis"},"\n","ev",{"VAR?":"affinity"},2,"-","/ev",{"VAR=":"affinity","re":true},{"->":"round_2.part_2"},{"#f":5}],"#f":5}]}],{"#f":1}],"part_2":[[["^The two of you fall into an easy stroll around the exercise yard as you chat. As you walk and talk you notice Otis is struggling to keep up.","\n","ev","str","^Getting tired?","/str","/ev",{"*":".^.c-0","flg":20},"ev","str","^Find a spot to sit","/str","/ev",{"*":".^.c-1","flg":20},{"c-0":["\n","^Well... I'm never going to say no to a little walk... you've just got long legs. ",{"#":"Name_Otis"},"\n","ev",{"VAR?":"affinity"},1,"-","/ev",{"VAR=":"affinity","re":true},{"->":".^.^.^.g-1"},{"#f":5}],"c-1":["^ ","\n","^It's nice to sit and chat. I've only got these little legs, sometimes I get a little worn out. ",{"#":"Name_Otis"},"\n",{"->":".^.^.^.g-1"},{"#f":5}],"#f":5,"#n":"g-0"}],{"g-1":["^So, do you go for lots of longer walks?","\n","ev","str","^Who doesn't!?","/str",{"VAR?":"likes_walks"},6,">","/ev",{"*":".^.c-2","flg":21},"ev","str","^Yeah.","/str","/ev",{"*":".^.c-3","flg":20},"ev","str","^Nature AmIRite?","/str",{"VAR?":"active"},6,">","/ev",{"*":".^.c-4","flg":21},"ev","str","^Meh.","/str","/ev",{"*":".^.c-5","flg":20},["ev",{"^->":"round_2.part_2.0.g-1.32.$r1"},{"temp=":"$r"},"str",{"->":".^.s"},[{"#n":"$r1"}],"/str",{"VAR?":"active"},4,"<","/ev",{"*":".^.^.c-6","flg":19},{"s":["^I much prefer a cozy armchair.",{"->":"$r","var":true},null]}],{"c-2":["\n","ev",{"VAR?":"affinity"},3,"-","/ev",{"VAR=":"affinity","re":true},"done",{"#f":5}],"c-3":["^Oh, yeah.","\n","ev",{"VAR?":"likes_walks"},1,"+","/ev",{"VAR=":"likes_walks","re":true},"ev",{"VAR?":"affinity"},1,"-","/ev",{"VAR=":"affinity","re":true},"done",{"#f":5}],"c-4":["\n","ev",{"VAR?":"active"},1,"+","/ev",{"VAR=":"active","re":true},"ev",{"VAR?":"affinity"},1,"-","/ev",{"VAR=":"affinity","re":true},"done",{"#f":5}],"c-5":["^ I don't mind them, it's nice to get out sometimes.","\n","done",{"#f":5}],"c-6":["ev",{"^->":"round_2.part_2.0.g-1.c-6.$r2"},"/ev",{"temp=":"$r"},{"->":".^.^.32.s"},[{"#n":"$r2"}],"\n","ev",{"VAR?":"likes_walks"},1,"-","/ev",{"VAR=":"likes_walks","re":true},"done",{"#f":5}],"#f":5}]}],{"#f":1}],"#f":1}],"round_3":[{"->":".^.part_1"},{"part_1":[{"->":".^.^.part_2"},{"#f":1}],"part_2":[{"->":".^.^.part_3"},{"#f":1}],"part_3":["done",{"#f":1}],"#f":1}],"global decl":["ev",5,{"VAR=":"likes_dogs"},5,{"VAR=":"likes_cats"},5,{"VAR=":"likes_kids"},5,{"VAR=":"likes_walks"},5,{"VAR=":"smart"},5,{"VAR=":"active"},5,{"VAR=":"playful"},false,{"VAR=":"has_dog"},true,{"VAR=":"spencer_available"},true,{"VAR=":"pablo_available"},true,{"VAR=":"vega_available"},true,{"VAR=":"ted_available"},true,{"VAR=":"chase_available"},true,{"VAR=":"otis_available"},true,{"VAR=":"betsy_available"},true,{"VAR=":"buddy_available"},true,{"VAR=":"stanley_available"},true,{"VAR=":"freya_available"},true,{"VAR=":"solly_available"},true,{"VAR=":"flo_available"},true,{"VAR=":"betty_available"},true,{"VAR=":"bisquit_available"},true,{"VAR=":"cesar_available"},true,{"VAR=":"sissy_available"},true,{"VAR=":"taylor_available"},true,{"VAR=":"woody_available"},true,{"VAR=":"bouncer_available"},true,{"VAR=":"freddie_available"},true,{"VAR=":"rusty_available"},4,{"VAR=":"affinity"},"/ev","end",null],"#f":1}],"listDefs":{}}